{
	"info": {
		"_postman_id": "29b0145f-0361-4a46-9e39-0cfa286a6624",
		"name": "MeetingPlanner/meetingTest",
		"schema": "https://schema.getpostman.com/json/collection/v2.1.0/collection.json",
		"_exporter_id": "34556504"
	},
	"item": [
		{
			"name": "meetingTest",
			"request": {
				"method": "POST",
				"header": [],
				"body": {
					"mode": "raw",
					"raw": "{\r\n    \"name\":\"Reunion 4\",\r\n    \"startTime\":\"11:00:00\",\r\n    \"endTime\":\"21:00:00\",\r\n    \"meetingDate\":\"2024-05-30\",\r\n    \"numberOfpeople\":18,\r\n    \"meetingType\":\"VC\"\r\n}",
					"options": {
						"raw": {
							"language": "json"
						}
					}
				},
				"url": {
					"raw": "localhost:8080/api/addMeetingOrder",
					"host": [
						"localhost"
					],
					"port": "8080",
					"path": [
						"api",
						"addMeetingOrder"
					]
				}
			},
			"response": []
		},
		{
			"name": "meetingTest",
			"request": {
				"method": "PUT",
				"header": [],
				"body": {
					"mode": "raw",
					"raw": "{\r\n    \"name\":\"Reunion des Directeurs\",\r\n    \"startTime\":\"09:00:00\",\r\n    \"endTime\":\"10:00:00\",\r\n    \"meetingDate\":\"2024-05-30\",\r\n    \"numberOfpeople\":8,\r\n    \"meetingType\":\"VC\"\r\n}",
					"options": {
						"raw": {
							"language": "json"
						}
					}
				},
				"url": {
					"raw": "localhost:8080/api/updateMeeting/1",
					"host": [
						"localhost"
					],
					"port": "8080",
					"path": [
						"api",
						"updateMeeting",
						"1"
					]
				}
			},
			"response": []
		},
		{
			"name": "meetingTest",
			"request": {
				"method": "DELETE",
				"header": [],
				"body": {
					"mode": "raw",
					"raw": "",
					"options": {
						"raw": {
							"language": "json"
						}
					}
				},
				"url": {
					"raw": "localhost:8080/api/deleteMeeting/1",
					"host": [
						"localhost"
					],
					"port": "8080",
					"path": [
						"api",
						"deleteMeeting",
						"1"
					]
				}
			},
			"response": []
		},
		{
			"name": "meetingTest",
			"protocolProfileBehavior": {
				"disableBodyPruning": true
			},
			"request": {
				"method": "GET",
				"header": [],
				"body": {
					"mode": "raw",
					"raw": "",
					"options": {
						"raw": {
							"language": "json"
						}
					}
				},
				"url": {
					"raw": "localhost:8080/api/allMeetingOrder",
					"host": [
						"localhost"
					],
					"port": "8080",
					"path": [
						"api",
						"allMeetingOrder"
					]
				}
			},
			"response": []
		}
	]
}